{
	"format_version": "1.12.0",
	"minecraft:geometry": [
		{
			"description": {
				"identifier": "geometry.air-titan-v2",
				"texture_width": 512,
				"texture_height": 512,
				"visible_bounds_width": 16,
				"visible_bounds_height": 15,
				"visible_bounds_offset": [0, 0.5, 0]
			},
			"bones": [
				{
					"name": "aura_ring",
					"pivot": [0, 0, 0],
					"cubes": [
						{
							"origin": [96, -48, -5.5],
							"size": [12, 96, 11],
							"uv": {
								"north": {"uv": [103, 273], "uv_size": [12, 96]},
								"east": {"uv": [92, 273], "uv_size": [11, 96]},
								"south": {"uv": [126, 273], "uv_size": [12, 96]},
								"west": {"uv": [115, 273], "uv_size": [11, 96]},
								"up": {"uv": [103, 262], "uv_size": [12, 11]},
								"down": {"uv": [115, 273], "uv_size": [12, -11]}
							}
						},
						{
							"origin": [-108, -48, -5.5],
							"size": [12, 96, 11],
							"uv": {
								"north": {"uv": [57, 273], "uv_size": [12, 96]},
								"east": {"uv": [46, 273], "uv_size": [11, 96]},
								"south": {"uv": [80, 273], "uv_size": [12, 96]},
								"west": {"uv": [69, 273], "uv_size": [11, 96]},
								"up": {"uv": [57, 262], "uv_size": [12, 11]},
								"down": {"uv": [69, 273], "uv_size": [12, -11]}
							}
						},
						{
							"origin": [-104, -4, -6.5],
							"size": [4, 9, 13],
							"uv": {
								"north": {"uv": [36, 420], "uv_size": [4, 9]},
								"east": {"uv": [23, 420], "uv_size": [13, 9]},
								"south": {"uv": [53, 420], "uv_size": [4, 9]},
								"west": {"uv": [40, 420], "uv_size": [13, 9]},
								"up": {"uv": [36, 407], "uv_size": [4, 13]},
								"down": {"uv": [40, 420], "uv_size": [4, -13]}
							}
						},
						{
							"origin": [100, -4, -6.5],
							"size": [4, 9, 13],
							"uv": {
								"north": {"uv": [36, 420], "uv_size": [4, 9]},
								"east": {"uv": [23, 420], "uv_size": [13, 9]},
								"south": {"uv": [53, 420], "uv_size": [4, 9]},
								"west": {"uv": [40, 420], "uv_size": [13, 9]},
								"up": {"uv": [36, 407], "uv_size": [4, 13]},
								"down": {"uv": [40, 420], "uv_size": [4, -13]}
							}
						},
						{
							"origin": [-104, 11, -6.5],
							"size": [4, 10, 13],
							"uv": {
								"north": {"uv": [36, 420], "uv_size": [4, 10]},
								"east": {"uv": [23, 420], "uv_size": [13, 10]},
								"south": {"uv": [53, 420], "uv_size": [4, 10]},
								"west": {"uv": [40, 420], "uv_size": [13, 10]},
								"up": {"uv": [36, 407], "uv_size": [4, 13]},
								"down": {"uv": [40, 420], "uv_size": [4, -13]}
							}
						},
						{
							"origin": [-104, 29, -6.5],
							"size": [4, 17, 13],
							"uv": {
								"north": {"uv": [36, 420], "uv_size": [4, 17]},
								"east": {"uv": [23, 420], "uv_size": [13, 17]},
								"south": {"uv": [53, 420], "uv_size": [4, 17]},
								"west": {"uv": [40, 420], "uv_size": [13, 17]},
								"up": {"uv": [36, 407], "uv_size": [4, 13]},
								"down": {"uv": [40, 420], "uv_size": [4, -13]}
							}
						},
						{
							"origin": [-104, -20, -6.5],
							"size": [4, 10, 13],
							"uv": {
								"north": {"uv": [36, 420], "uv_size": [4, 10]},
								"east": {"uv": [23, 420], "uv_size": [13, 10]},
								"south": {"uv": [53, 420], "uv_size": [4, 10]},
								"west": {"uv": [40, 420], "uv_size": [13, 10]},
								"up": {"uv": [36, 407], "uv_size": [4, 13]},
								"down": {"uv": [40, 420], "uv_size": [4, -13]}
							}
						},
						{
							"origin": [-104, -46, -6.5],
							"size": [4, 17, 13],
							"uv": {
								"north": {"uv": [36, 420], "uv_size": [4, 17]},
								"east": {"uv": [23, 420], "uv_size": [13, 17]},
								"south": {"uv": [53, 420], "uv_size": [4, 17]},
								"west": {"uv": [40, 420], "uv_size": [13, 17]},
								"up": {"uv": [36, 407], "uv_size": [4, 13]},
								"down": {"uv": [40, 420], "uv_size": [4, -13]}
							}
						},
						{
							"origin": [-48, 96, -5.5],
							"size": [96, 12, 11],
							"uv": {
								"north": {"uv": [257, 161], "uv_size": [96, 12]},
								"east": {"uv": [246, 161], "uv_size": [11, 12]},
								"south": {"uv": [364, 161], "uv_size": [96, 12]},
								"west": {"uv": [353, 161], "uv_size": [11, 12]},
								"up": {"uv": [257, 150], "uv_size": [96, 11]},
								"down": {"uv": [353, 161], "uv_size": [96, -11]}
							}
						},
						{
							"origin": [-48, -108, -5.5],
							"size": [96, 12, 11],
							"uv": {
								"north": {"uv": [257, 161], "uv_size": [96, 12]},
								"east": {"uv": [246, 161], "uv_size": [11, 12]},
								"south": {"uv": [364, 161], "uv_size": [96, 12]},
								"west": {"uv": [353, 161], "uv_size": [11, 12]},
								"up": {"uv": [257, 150], "uv_size": [96, 11]},
								"down": {"uv": [353, 161], "uv_size": [96, -11]}
							}
						},
						{
							"origin": [96, 48, -2.5],
							"size": [12, 84.85, 5],
							"pivot": [108, 48, -9.5],
							"rotation": [0, 0, -45],
							"uv": {
								"north": {"uv": [130, 132], "uv_size": [12, 84]},
								"east": {"uv": [125, 132], "uv_size": [5, 84]},
								"south": {"uv": [147, 132], "uv_size": [12, 84]},
								"west": {"uv": [142, 132], "uv_size": [5, 84]},
								"up": {"uv": [130, 127], "uv_size": [12, 5]},
								"down": {"uv": [142, 132], "uv_size": [12, -5]}
							}
						},
						{
							"origin": [-108, 48, -2.5],
							"size": [12, 84.85, 5],
							"pivot": [-108, 48, -9.5],
							"rotation": [0, 0, 45],
							"uv": {
								"north": {"uv": [130, 5], "uv_size": [12, 84]},
								"east": {"uv": [125, 5], "uv_size": [5, 84]},
								"south": {"uv": [147, 5], "uv_size": [12, 84]},
								"west": {"uv": [142, 5], "uv_size": [5, 84]},
								"up": {"uv": [130, 0], "uv_size": [12, 5]},
								"down": {"uv": [142, 5], "uv_size": [12, -5]}
							}
						},
						{
							"origin": [-108, -132.85, -2.5],
							"size": [12, 84.85, 5],
							"pivot": [-108, -48, -9.5],
							"rotation": [0, 0, -45],
							"uv": {
								"north": {"uv": [130, 132], "uv_size": [12, 84]},
								"east": {"uv": [125, 132], "uv_size": [5, 84]},
								"south": {"uv": [147, 132], "uv_size": [12, 84]},
								"west": {"uv": [142, 132], "uv_size": [5, 84]},
								"up": {"uv": [130, 127], "uv_size": [12, 5]},
								"down": {"uv": [142, 132], "uv_size": [12, -5]}
							}
						},
						{
							"origin": [96, -132.85, -2.5],
							"size": [12, 84.85, 5],
							"pivot": [108, -48, -9.5],
							"rotation": [0, 0, 45],
							"uv": {
								"north": {"uv": [130, 5], "uv_size": [12, 84]},
								"east": {"uv": [125, 5], "uv_size": [5, 84]},
								"south": {"uv": [147, 5], "uv_size": [12, 84]},
								"west": {"uv": [142, 5], "uv_size": [5, 84]},
								"up": {"uv": [130, 0], "uv_size": [12, 5]},
								"down": {"uv": [142, 5], "uv_size": [12, -5]}
							}
						},
						{
							"origin": [100, -46, -6.5],
							"size": [4, 17, 13],
							"uv": {
								"north": {"uv": [40, 420], "uv_size": [-4, 17]},
								"east": {"uv": [53, 420], "uv_size": [-13, 17]},
								"south": {"uv": [57, 420], "uv_size": [-4, 17]},
								"west": {"uv": [36, 420], "uv_size": [-13, 17]},
								"up": {"uv": [40, 407], "uv_size": [-4, 13]},
								"down": {"uv": [44, 420], "uv_size": [-4, -13]}
							}
						},
						{
							"origin": [100, -20, -6.5],
							"size": [4, 10, 13],
							"uv": {
								"north": {"uv": [40, 420], "uv_size": [-4, 10]},
								"east": {"uv": [53, 420], "uv_size": [-13, 10]},
								"south": {"uv": [57, 420], "uv_size": [-4, 10]},
								"west": {"uv": [36, 420], "uv_size": [-13, 10]},
								"up": {"uv": [40, 407], "uv_size": [-4, 13]},
								"down": {"uv": [44, 420], "uv_size": [-4, -13]}
							}
						},
						{
							"origin": [100, 29, -6.5],
							"size": [4, 17, 13],
							"uv": {
								"north": {"uv": [40, 420], "uv_size": [-4, 17]},
								"east": {"uv": [53, 420], "uv_size": [-13, 17]},
								"south": {"uv": [57, 420], "uv_size": [-4, 17]},
								"west": {"uv": [36, 420], "uv_size": [-13, 17]},
								"up": {"uv": [40, 407], "uv_size": [-4, 13]},
								"down": {"uv": [44, 420], "uv_size": [-4, -13]}
							}
						},
						{
							"origin": [100, 11, -6.5],
							"size": [4, 10, 13],
							"uv": {
								"north": {"uv": [40, 420], "uv_size": [-4, 10]},
								"east": {"uv": [53, 420], "uv_size": [-13, 10]},
								"south": {"uv": [57, 420], "uv_size": [-4, 10]},
								"west": {"uv": [36, 420], "uv_size": [-13, 10]},
								"up": {"uv": [40, 407], "uv_size": [-4, 13]},
								"down": {"uv": [44, 420], "uv_size": [-4, -13]}
							}
						},
						{
							"origin": [-28, 100, -6.5],
							"size": [12, 4, 13],
							"uv": {
								"north": {"uv": [36, 420], "uv_size": [12, 4]},
								"east": {"uv": [23, 420], "uv_size": [13, 4]},
								"south": {"uv": [61, 420], "uv_size": [12, 4]},
								"west": {"uv": [48, 420], "uv_size": [13, 4]},
								"up": {"uv": [36, 407], "uv_size": [12, 13]},
								"down": {"uv": [48, 420], "uv_size": [12, -13]}
							}
						},
						{
							"origin": [-28, -104, -6.5],
							"size": [12, 4, 13],
							"uv": {
								"north": {"uv": [48, 420], "uv_size": [-12, 4]},
								"east": {"uv": [61, 420], "uv_size": [-13, 4]},
								"south": {"uv": [73, 420], "uv_size": [-12, 4]},
								"west": {"uv": [36, 420], "uv_size": [-13, 4]},
								"up": {"uv": [48, 407], "uv_size": [-12, 13]},
								"down": {"uv": [60, 420], "uv_size": [-12, -13]}
							}
						},
						{
							"origin": [-5, -104, -6.5],
							"size": [11, 4, 13],
							"uv": {
								"north": {"uv": [47, 420], "uv_size": [-11, 4]},
								"east": {"uv": [60, 420], "uv_size": [-13, 4]},
								"south": {"uv": [71, 420], "uv_size": [-11, 4]},
								"west": {"uv": [36, 420], "uv_size": [-13, 4]},
								"up": {"uv": [47, 407], "uv_size": [-11, 13]},
								"down": {"uv": [58, 420], "uv_size": [-11, -13]}
							}
						},
						{
							"origin": [16, -104, -6.5],
							"size": [12, 4, 13],
							"uv": {
								"north": {"uv": [48, 420], "uv_size": [-12, 4]},
								"east": {"uv": [61, 420], "uv_size": [-13, 4]},
								"south": {"uv": [73, 420], "uv_size": [-12, 4]},
								"west": {"uv": [36, 420], "uv_size": [-13, 4]},
								"up": {"uv": [48, 407], "uv_size": [-12, 13]},
								"down": {"uv": [60, 420], "uv_size": [-12, -13]}
							}
						},
						{
							"origin": [16, 100, -6.5],
							"size": [12, 4, 13],
							"uv": {
								"north": {"uv": [48, 420], "uv_size": [-12, 4]},
								"east": {"uv": [61, 420], "uv_size": [-13, 4]},
								"south": {"uv": [73, 420], "uv_size": [-12, 4]},
								"west": {"uv": [36, 420], "uv_size": [-13, 4]},
								"up": {"uv": [48, 407], "uv_size": [-12, 13]},
								"down": {"uv": [60, 420], "uv_size": [-12, -13]}
							}
						},
						{
							"origin": [-7, 100, -6.5],
							"size": [14, 4, 13],
							"uv": {
								"north": {"uv": [50, 420], "uv_size": [-14, 4]},
								"east": {"uv": [63, 420], "uv_size": [-13, 4]},
								"south": {"uv": [77, 420], "uv_size": [-14, 4]},
								"west": {"uv": [36, 420], "uv_size": [-13, 4]},
								"up": {"uv": [50, 407], "uv_size": [-14, 13]},
								"down": {"uv": [64, 420], "uv_size": [-14, -13]}
							}
						}
					]
				},
				{
					"name": "aura_ring3",
					"pivot": [0, 0, 0],
					"cubes": [
						{
							"origin": [-49.92, -5.72, -112.32],
							"size": [99.84, 11.44, 12.48],
							"uv": {
								"north": {"uv": [115, 273], "uv_size": [11, 96]},
								"east": {"uv": [127, 262], "uv_size": [-12, 11]},
								"south": {"uv": [92, 273], "uv_size": [11, 96]},
								"west": {"uv": [115, 273], "uv_size": [-12, -11]},
								"up": {"uv": [115, 369], "uv_size": [-12, -96]},
								"down": {"uv": [138, 369], "uv_size": [-12, -96]}
							}
						},
						{
							"origin": [-49.92, -5.72, 99.84],
							"size": [99.84, 11.44, 12.48],
							"uv": {
								"north": {"uv": [69, 273], "uv_size": [11, 96]},
								"east": {"uv": [81, 262], "uv_size": [-12, 11]},
								"south": {"uv": [46, 273], "uv_size": [11, 96]},
								"west": {"uv": [69, 273], "uv_size": [-12, -11]},
								"up": {"uv": [69, 369], "uv_size": [-12, -96]},
								"down": {"uv": [92, 369], "uv_size": [-12, -96]}
							}
						},
						{
							"origin": [-4.16, -6.76, 104],
							"size": [9.36, 13.52, 4.16],
							"uv": {
								"north": {"uv": [40, 420], "uv_size": [13, 9]},
								"east": {"uv": [44, 407], "uv_size": [-4, 13]},
								"south": {"uv": [23, 420], "uv_size": [13, 9]},
								"west": {"uv": [40, 420], "uv_size": [-4, -13]},
								"up": {"uv": [40, 429], "uv_size": [-4, -9]},
								"down": {"uv": [57, 429], "uv_size": [-4, -9]}
							}
						},
						{
							"origin": [-4.16, -6.76, -108.16],
							"size": [9.36, 13.52, 4.16],
							"uv": {
								"north": {"uv": [40, 420], "uv_size": [13, 9]},
								"east": {"uv": [44, 407], "uv_size": [-4, 13]},
								"south": {"uv": [23, 420], "uv_size": [13, 9]},
								"west": {"uv": [40, 420], "uv_size": [-4, -13]},
								"up": {"uv": [40, 429], "uv_size": [-4, -9]},
								"down": {"uv": [57, 429], "uv_size": [-4, -9]}
							}
						},
						{
							"origin": [11.44, -6.76, 104],
							"size": [10.4, 13.52, 4.16],
							"uv": {
								"north": {"uv": [40, 420], "uv_size": [13, 10]},
								"east": {"uv": [44, 407], "uv_size": [-4, 13]},
								"south": {"uv": [23, 420], "uv_size": [13, 10]},
								"west": {"uv": [40, 420], "uv_size": [-4, -13]},
								"up": {"uv": [40, 430], "uv_size": [-4, -10]},
								"down": {"uv": [57, 430], "uv_size": [-4, -10]}
							}
						},
						{
							"origin": [30.16, -6.76, 104],
							"size": [17.68, 13.52, 4.16],
							"uv": {
								"north": {"uv": [40, 420], "uv_size": [13, 17]},
								"east": {"uv": [44, 407], "uv_size": [-4, 13]},
								"south": {"uv": [23, 420], "uv_size": [13, 17]},
								"west": {"uv": [40, 420], "uv_size": [-4, -13]},
								"up": {"uv": [40, 437], "uv_size": [-4, -17]},
								"down": {"uv": [57, 437], "uv_size": [-4, -17]}
							}
						},
						{
							"origin": [-20.8, -6.76, 104],
							"size": [10.4, 13.52, 4.16],
							"uv": {
								"north": {"uv": [40, 420], "uv_size": [13, 10]},
								"east": {"uv": [44, 407], "uv_size": [-4, 13]},
								"south": {"uv": [23, 420], "uv_size": [13, 10]},
								"west": {"uv": [40, 420], "uv_size": [-4, -13]},
								"up": {"uv": [40, 430], "uv_size": [-4, -10]},
								"down": {"uv": [57, 430], "uv_size": [-4, -10]}
							}
						},
						{
							"origin": [-47.84, -6.76, 104],
							"size": [17.68, 13.52, 4.16],
							"uv": {
								"north": {"uv": [40, 420], "uv_size": [13, 17]},
								"east": {"uv": [44, 407], "uv_size": [-4, 13]},
								"south": {"uv": [23, 420], "uv_size": [13, 17]},
								"west": {"uv": [40, 420], "uv_size": [-4, -13]},
								"up": {"uv": [40, 437], "uv_size": [-4, -17]},
								"down": {"uv": [57, 437], "uv_size": [-4, -17]}
							}
						},
						{
							"origin": [99.84, -5.72, -49.92],
							"size": [12.48, 11.44, 99.84],
							"uv": {
								"north": {"uv": [353, 161], "uv_size": [11, 12]},
								"east": {"uv": [449, 150], "uv_size": [-96, 11]},
								"south": {"uv": [246, 161], "uv_size": [11, 12]},
								"west": {"uv": [353, 161], "uv_size": [-96, -11]},
								"up": {"uv": [353, 173], "uv_size": [-96, -12]},
								"down": {"uv": [460, 173], "uv_size": [-96, -12]}
							}
						},
						{
							"origin": [-112.32, -5.72, -49.92],
							"size": [12.48, 11.44, 99.84],
							"uv": {
								"north": {"uv": [353, 161], "uv_size": [11, 12]},
								"east": {"uv": [449, 150], "uv_size": [-96, 11]},
								"south": {"uv": [246, 161], "uv_size": [11, 12]},
								"west": {"uv": [353, 161], "uv_size": [-96, -11]},
								"up": {"uv": [353, 173], "uv_size": [-96, -12]},
								"down": {"uv": [460, 173], "uv_size": [-96, -12]}
							}
						},
						{
							"origin": [49.92, -2.6, -112.32],
							"size": [88.244, 5.2, 12.48],
							"pivot": [49.92, 9.88, -112.32],
							"rotation": [0, -45, 0],
							"uv": {
								"north": {"uv": [142, 132], "uv_size": [5, 84]},
								"east": {"uv": [154, 127], "uv_size": [-12, 5]},
								"south": {"uv": [125, 132], "uv_size": [5, 84]},
								"west": {"uv": [142, 132], "uv_size": [-12, -5]},
								"up": {"uv": [142, 216], "uv_size": [-12, -84]},
								"down": {"uv": [159, 216], "uv_size": [-12, -84]}
							}
						},
						{
							"origin": [49.92, -2.6, 99.84],
							"size": [88.244, 5.2, 12.48],
							"pivot": [49.92, 9.88, 112.32],
							"rotation": [0, 45, 0],
							"uv": {
								"north": {"uv": [142, 5], "uv_size": [5, 84]},
								"east": {"uv": [154, 0], "uv_size": [-12, 5]},
								"south": {"uv": [125, 5], "uv_size": [5, 84]},
								"west": {"uv": [142, 5], "uv_size": [-12, -5]},
								"up": {"uv": [142, 89], "uv_size": [-12, -84]},
								"down": {"uv": [159, 89], "uv_size": [-12, -84]}
							}
						},
						{
							"origin": [-138.164, -2.6, 99.84],
							"size": [88.244, 5.2, 12.48],
							"pivot": [-49.92, 9.88, 112.32],
							"rotation": [0, -45, 0],
							"uv": {
								"north": {"uv": [142, 132], "uv_size": [5, 84]},
								"east": {"uv": [154, 127], "uv_size": [-12, 5]},
								"south": {"uv": [125, 132], "uv_size": [5, 84]},
								"west": {"uv": [142, 132], "uv_size": [-12, -5]},
								"up": {"uv": [142, 216], "uv_size": [-12, -84]},
								"down": {"uv": [159, 216], "uv_size": [-12, -84]}
							}
						},
						{
							"origin": [-138.164, -2.6, -112.32],
							"size": [88.244, 5.2, 12.48],
							"pivot": [-49.92, 9.88, -112.32],
							"rotation": [0, 45, 0],
							"uv": {
								"north": {"uv": [142, 5], "uv_size": [5, 84]},
								"east": {"uv": [154, 0], "uv_size": [-12, 5]},
								"south": {"uv": [125, 5], "uv_size": [5, 84]},
								"west": {"uv": [142, 5], "uv_size": [-12, -5]},
								"up": {"uv": [142, 89], "uv_size": [-12, -84]},
								"down": {"uv": [159, 89], "uv_size": [-12, -84]}
							}
						},
						{
							"origin": [-47.84, -6.76, -108.16],
							"size": [17.68, 13.52, 4.16],
							"uv": {
								"north": {"uv": [36, 420], "uv_size": [-13, 17]},
								"east": {"uv": [40, 407], "uv_size": [4, 13]},
								"south": {"uv": [53, 420], "uv_size": [-13, 17]},
								"west": {"uv": [36, 420], "uv_size": [4, -13]},
								"up": {"uv": [36, 437], "uv_size": [4, -17]},
								"down": {"uv": [53, 437], "uv_size": [4, -17]}
							}
						},
						{
							"origin": [-20.8, -6.76, -108.16],
							"size": [10.4, 13.52, 4.16],
							"uv": {
								"north": {"uv": [36, 420], "uv_size": [-13, 10]},
								"east": {"uv": [40, 407], "uv_size": [4, 13]},
								"south": {"uv": [53, 420], "uv_size": [-13, 10]},
								"west": {"uv": [36, 420], "uv_size": [4, -13]},
								"up": {"uv": [36, 430], "uv_size": [4, -10]},
								"down": {"uv": [53, 430], "uv_size": [4, -10]}
							}
						},
						{
							"origin": [30.16, -6.76, -108.16],
							"size": [17.68, 13.52, 4.16],
							"uv": {
								"north": {"uv": [36, 420], "uv_size": [-13, 17]},
								"east": {"uv": [40, 407], "uv_size": [4, 13]},
								"south": {"uv": [53, 420], "uv_size": [-13, 17]},
								"west": {"uv": [36, 420], "uv_size": [4, -13]},
								"up": {"uv": [36, 437], "uv_size": [4, -17]},
								"down": {"uv": [53, 437], "uv_size": [4, -17]}
							}
						},
						{
							"origin": [11.44, -6.76, -108.16],
							"size": [10.4, 13.52, 4.16],
							"uv": {
								"north": {"uv": [36, 420], "uv_size": [-13, 10]},
								"east": {"uv": [40, 407], "uv_size": [4, 13]},
								"south": {"uv": [53, 420], "uv_size": [-13, 10]},
								"west": {"uv": [36, 420], "uv_size": [4, -13]},
								"up": {"uv": [36, 430], "uv_size": [4, -10]},
								"down": {"uv": [53, 430], "uv_size": [4, -10]}
							}
						},
						{
							"origin": [104, -6.76, 16.64],
							"size": [4.16, 13.52, 12.48],
							"uv": {
								"north": {"uv": [48, 420], "uv_size": [13, 4]},
								"east": {"uv": [60, 407], "uv_size": [-12, 13]},
								"south": {"uv": [23, 420], "uv_size": [13, 4]},
								"west": {"uv": [48, 420], "uv_size": [-12, -13]},
								"up": {"uv": [48, 424], "uv_size": [-12, -4]},
								"down": {"uv": [73, 424], "uv_size": [-12, -4]}
							}
						},
						{
							"origin": [-108.16, -6.76, 16.64],
							"size": [4.16, 13.52, 12.48],
							"uv": {
								"north": {"uv": [36, 420], "uv_size": [-13, 4]},
								"east": {"uv": [48, 407], "uv_size": [12, 13]},
								"south": {"uv": [61, 420], "uv_size": [-13, 4]},
								"west": {"uv": [36, 420], "uv_size": [12, -13]},
								"up": {"uv": [36, 424], "uv_size": [12, -4]},
								"down": {"uv": [61, 424], "uv_size": [12, -4]}
							}
						},
						{
							"origin": [-108.16, -6.76, -6.24],
							"size": [4.16, 13.52, 11.44],
							"uv": {
								"north": {"uv": [36, 420], "uv_size": [-13, 4]},
								"east": {"uv": [47, 407], "uv_size": [11, 13]},
								"south": {"uv": [60, 420], "uv_size": [-13, 4]},
								"west": {"uv": [36, 420], "uv_size": [11, -13]},
								"up": {"uv": [36, 424], "uv_size": [11, -4]},
								"down": {"uv": [60, 424], "uv_size": [11, -4]}
							}
						},
						{
							"origin": [-108.16, -6.76, -29.12],
							"size": [4.16, 13.52, 12.48],
							"uv": {
								"north": {"uv": [36, 420], "uv_size": [-13, 4]},
								"east": {"uv": [48, 407], "uv_size": [12, 13]},
								"south": {"uv": [61, 420], "uv_size": [-13, 4]},
								"west": {"uv": [36, 420], "uv_size": [12, -13]},
								"up": {"uv": [36, 424], "uv_size": [12, -4]},
								"down": {"uv": [61, 424], "uv_size": [12, -4]}
							}
						},
						{
							"origin": [104, -6.76, -29.12],
							"size": [4.16, 13.52, 12.48],
							"uv": {
								"north": {"uv": [36, 420], "uv_size": [-13, 4]},
								"east": {"uv": [48, 407], "uv_size": [12, 13]},
								"south": {"uv": [61, 420], "uv_size": [-13, 4]},
								"west": {"uv": [36, 420], "uv_size": [12, -13]},
								"up": {"uv": [36, 424], "uv_size": [12, -4]},
								"down": {"uv": [61, 424], "uv_size": [12, -4]}
							}
						},
						{
							"origin": [104, -6.76, -7.28],
							"size": [4.16, 13.52, 14.56],
							"uv": {
								"north": {"uv": [36, 420], "uv_size": [-13, 4]},
								"east": {"uv": [50, 407], "uv_size": [14, 13]},
								"south": {"uv": [63, 420], "uv_size": [-13, 4]},
								"west": {"uv": [36, 420], "uv_size": [14, -13]},
								"up": {"uv": [36, 424], "uv_size": [14, -4]},
								"down": {"uv": [63, 424], "uv_size": [14, -4]}
							}
						}
					]
				},
				{
					"name": "aura_ring2",
					"pivot": [0, 0, 0],
					"cubes": [
						{
							"origin": [-6.05, -52.8, -118.8],
							"size": [12.1, 105.6, 13.2],
							"uv": {
								"north": {"uv": [115, 273], "uv_size": [11, 96]},
								"east": {"uv": [103, 273], "uv_size": [12, 96]},
								"south": {"uv": [92, 273], "uv_size": [11, 96]},
								"west": {"uv": [126, 273], "uv_size": [12, 96]},
								"up": {"uv": [103, 262], "uv_size": [12, 11]},
								"down": {"uv": [115, 273], "uv_size": [12, -11]}
							}
						},
						{
							"origin": [-6.05, -52.8, 105.6],
							"size": [12.1, 105.6, 13.2],
							"uv": {
								"north": {"uv": [69, 273], "uv_size": [11, 96]},
								"east": {"uv": [57, 273], "uv_size": [12, 96]},
								"south": {"uv": [46, 273], "uv_size": [11, 96]},
								"west": {"uv": [80, 273], "uv_size": [12, 96]},
								"up": {"uv": [57, 262], "uv_size": [12, 11]},
								"down": {"uv": [69, 273], "uv_size": [12, -11]}
							}
						},
						{
							"origin": [-7.15, -4.4, 110],
							"size": [14.3, 9.9, 4.4],
							"uv": {
								"north": {"uv": [40, 420], "uv_size": [13, 9]},
								"east": {"uv": [36, 420], "uv_size": [4, 9]},
								"south": {"uv": [23, 420], "uv_size": [13, 9]},
								"west": {"uv": [53, 420], "uv_size": [4, 9]},
								"up": {"uv": [36, 407], "uv_size": [4, 13]},
								"down": {"uv": [40, 420], "uv_size": [4, -13]}
							}
						},
						{
							"origin": [-7.15, -4.4, -114.4],
							"size": [14.3, 9.9, 4.4],
							"uv": {
								"north": {"uv": [40, 420], "uv_size": [13, 9]},
								"east": {"uv": [36, 420], "uv_size": [4, 9]},
								"south": {"uv": [23, 420], "uv_size": [13, 9]},
								"west": {"uv": [53, 420], "uv_size": [4, 9]},
								"up": {"uv": [36, 407], "uv_size": [4, 13]},
								"down": {"uv": [40, 420], "uv_size": [4, -13]}
							}
						},
						{
							"origin": [-7.15, 12.1, 110],
							"size": [14.3, 11, 4.4],
							"uv": {
								"north": {"uv": [40, 420], "uv_size": [13, 10]},
								"east": {"uv": [36, 420], "uv_size": [4, 10]},
								"south": {"uv": [23, 420], "uv_size": [13, 10]},
								"west": {"uv": [53, 420], "uv_size": [4, 10]},
								"up": {"uv": [36, 407], "uv_size": [4, 13]},
								"down": {"uv": [40, 420], "uv_size": [4, -13]}
							}
						},
						{
							"origin": [-7.15, 31.9, 110],
							"size": [14.3, 18.7, 4.4],
							"uv": {
								"north": {"uv": [40, 420], "uv_size": [13, 17]},
								"east": {"uv": [36, 420], "uv_size": [4, 17]},
								"south": {"uv": [23, 420], "uv_size": [13, 17]},
								"west": {"uv": [53, 420], "uv_size": [4, 17]},
								"up": {"uv": [36, 407], "uv_size": [4, 13]},
								"down": {"uv": [40, 420], "uv_size": [4, -13]}
							}
						},
						{
							"origin": [-7.15, -22, 110],
							"size": [14.3, 11, 4.4],
							"uv": {
								"north": {"uv": [40, 420], "uv_size": [13, 10]},
								"east": {"uv": [36, 420], "uv_size": [4, 10]},
								"south": {"uv": [23, 420], "uv_size": [13, 10]},
								"west": {"uv": [53, 420], "uv_size": [4, 10]},
								"up": {"uv": [36, 407], "uv_size": [4, 13]},
								"down": {"uv": [40, 420], "uv_size": [4, -13]}
							}
						},
						{
							"origin": [-7.15, -50.6, 110],
							"size": [14.3, 18.7, 4.4],
							"uv": {
								"north": {"uv": [40, 420], "uv_size": [13, 17]},
								"east": {"uv": [36, 420], "uv_size": [4, 17]},
								"south": {"uv": [23, 420], "uv_size": [13, 17]},
								"west": {"uv": [53, 420], "uv_size": [4, 17]},
								"up": {"uv": [36, 407], "uv_size": [4, 13]},
								"down": {"uv": [40, 420], "uv_size": [4, -13]}
							}
						},
						{
							"origin": [-6.05, 105.6, -52.8],
							"size": [12.1, 13.2, 105.6],
							"uv": {
								"north": {"uv": [353, 161], "uv_size": [11, 12]},
								"east": {"uv": [257, 161], "uv_size": [96, 12]},
								"south": {"uv": [246, 161], "uv_size": [11, 12]},
								"west": {"uv": [364, 161], "uv_size": [96, 12]},
								"up": {"uv": [257, 150], "uv_size": [96, 11]},
								"down": {"uv": [353, 161], "uv_size": [96, -11]}
							}
						},
						{
							"origin": [-6.05, -118.8, -52.8],
							"size": [12.1, 13.2, 105.6],
							"uv": {
								"north": {"uv": [353, 161], "uv_size": [11, 12]},
								"east": {"uv": [257, 161], "uv_size": [96, 12]},
								"south": {"uv": [246, 161], "uv_size": [11, 12]},
								"west": {"uv": [364, 161], "uv_size": [96, 12]},
								"up": {"uv": [257, 150], "uv_size": [96, 11]},
								"down": {"uv": [353, 161], "uv_size": [96, -11]}
							}
						},
						{
							"origin": [-2.75, 52.8, -118.8],
							"size": [5.5, 93.335, 13.2],
							"pivot": [-10.45, 52.8, -118.8],
							"rotation": [-45, 0, 0],
							"uv": {
								"north": {"uv": [142, 132], "uv_size": [5, 84]},
								"east": {"uv": [130, 132], "uv_size": [12, 84]},
								"south": {"uv": [125, 132], "uv_size": [5, 84]},
								"west": {"uv": [147, 132], "uv_size": [12, 84]},
								"up": {"uv": [130, 127], "uv_size": [12, 5]},
								"down": {"uv": [142, 132], "uv_size": [12, -5]}
							}
						},
						{
							"origin": [-2.75, 52.8, 105.6],
							"size": [5.5, 93.335, 13.2],
							"pivot": [-10.45, 52.8, 118.8],
							"rotation": [45, 0, 0],
							"uv": {
								"north": {"uv": [142, 5], "uv_size": [5, 84]},
								"east": {"uv": [130, 5], "uv_size": [12, 84]},
								"south": {"uv": [125, 5], "uv_size": [5, 84]},
								"west": {"uv": [147, 5], "uv_size": [12, 84]},
								"up": {"uv": [130, 0], "uv_size": [12, 5]},
								"down": {"uv": [142, 5], "uv_size": [12, -5]}
							}
						},
						{
							"origin": [-2.75, -146.135, 105.6],
							"size": [5.5, 93.335, 13.2],
							"pivot": [-10.45, -52.8, 118.8],
							"rotation": [-45, 0, 0],
							"uv": {
								"north": {"uv": [142, 132], "uv_size": [5, 84]},
								"east": {"uv": [130, 132], "uv_size": [12, 84]},
								"south": {"uv": [125, 132], "uv_size": [5, 84]},
								"west": {"uv": [147, 132], "uv_size": [12, 84]},
								"up": {"uv": [130, 127], "uv_size": [12, 5]},
								"down": {"uv": [142, 132], "uv_size": [12, -5]}
							}
						},
						{
							"origin": [-2.75, -146.135, -118.8],
							"size": [5.5, 93.335, 13.2],
							"pivot": [-10.45, -52.8, -118.8],
							"rotation": [45, 0, 0],
							"uv": {
								"north": {"uv": [142, 5], "uv_size": [5, 84]},
								"east": {"uv": [130, 5], "uv_size": [12, 84]},
								"south": {"uv": [125, 5], "uv_size": [5, 84]},
								"west": {"uv": [147, 5], "uv_size": [12, 84]},
								"up": {"uv": [130, 0], "uv_size": [12, 5]},
								"down": {"uv": [142, 5], "uv_size": [12, -5]}
							}
						},
						{
							"origin": [-7.15, -50.6, -114.4],
							"size": [14.3, 18.7, 4.4],
							"uv": {
								"north": {"uv": [36, 420], "uv_size": [-13, 17]},
								"east": {"uv": [40, 420], "uv_size": [-4, 17]},
								"south": {"uv": [53, 420], "uv_size": [-13, 17]},
								"west": {"uv": [57, 420], "uv_size": [-4, 17]},
								"up": {"uv": [40, 407], "uv_size": [-4, 13]},
								"down": {"uv": [44, 420], "uv_size": [-4, -13]}
							}
						},
						{
							"origin": [-7.15, -22, -114.4],
							"size": [14.3, 11, 4.4],
							"uv": {
								"north": {"uv": [36, 420], "uv_size": [-13, 10]},
								"east": {"uv": [40, 420], "uv_size": [-4, 10]},
								"south": {"uv": [53, 420], "uv_size": [-13, 10]},
								"west": {"uv": [57, 420], "uv_size": [-4, 10]},
								"up": {"uv": [40, 407], "uv_size": [-4, 13]},
								"down": {"uv": [44, 420], "uv_size": [-4, -13]}
							}
						},
						{
							"origin": [-7.15, 31.9, -114.4],
							"size": [14.3, 18.7, 4.4],
							"uv": {
								"north": {"uv": [36, 420], "uv_size": [-13, 17]},
								"east": {"uv": [40, 420], "uv_size": [-4, 17]},
								"south": {"uv": [53, 420], "uv_size": [-13, 17]},
								"west": {"uv": [57, 420], "uv_size": [-4, 17]},
								"up": {"uv": [40, 407], "uv_size": [-4, 13]},
								"down": {"uv": [44, 420], "uv_size": [-4, -13]}
							}
						},
						{
							"origin": [-7.15, 12.1, -114.4],
							"size": [14.3, 11, 4.4],
							"uv": {
								"north": {"uv": [36, 420], "uv_size": [-13, 10]},
								"east": {"uv": [40, 420], "uv_size": [-4, 10]},
								"south": {"uv": [53, 420], "uv_size": [-13, 10]},
								"west": {"uv": [57, 420], "uv_size": [-4, 10]},
								"up": {"uv": [40, 407], "uv_size": [-4, 13]},
								"down": {"uv": [44, 420], "uv_size": [-4, -13]}
							}
						},
						{
							"origin": [-7.15, 110, 17.6],
							"size": [14.3, 4.4, 13.2],
							"uv": {
								"north": {"uv": [48, 420], "uv_size": [13, 4]},
								"east": {"uv": [36, 420], "uv_size": [12, 4]},
								"south": {"uv": [23, 420], "uv_size": [13, 4]},
								"west": {"uv": [61, 420], "uv_size": [12, 4]},
								"up": {"uv": [36, 407], "uv_size": [12, 13]},
								"down": {"uv": [48, 420], "uv_size": [12, -13]}
							}
						},
						{
							"origin": [-7.15, -114.4, 17.6],
							"size": [14.3, 4.4, 13.2],
							"uv": {
								"north": {"uv": [36, 420], "uv_size": [-13, 4]},
								"east": {"uv": [48, 420], "uv_size": [-12, 4]},
								"south": {"uv": [61, 420], "uv_size": [-13, 4]},
								"west": {"uv": [73, 420], "uv_size": [-12, 4]},
								"up": {"uv": [48, 407], "uv_size": [-12, 13]},
								"down": {"uv": [60, 420], "uv_size": [-12, -13]}
							}
						},
						{
							"origin": [-7.15, -114.4, -6.6],
							"size": [14.3, 4.4, 12.1],
							"uv": {
								"north": {"uv": [36, 420], "uv_size": [-13, 4]},
								"east": {"uv": [47, 420], "uv_size": [-11, 4]},
								"south": {"uv": [60, 420], "uv_size": [-13, 4]},
								"west": {"uv": [71, 420], "uv_size": [-11, 4]},
								"up": {"uv": [47, 407], "uv_size": [-11, 13]},
								"down": {"uv": [58, 420], "uv_size": [-11, -13]}
							}
						},
						{
							"origin": [-7.15, -114.4, -30.8],
							"size": [14.3, 4.4, 13.2],
							"uv": {
								"north": {"uv": [36, 420], "uv_size": [-13, 4]},
								"east": {"uv": [48, 420], "uv_size": [-12, 4]},
								"south": {"uv": [61, 420], "uv_size": [-13, 4]},
								"west": {"uv": [73, 420], "uv_size": [-12, 4]},
								"up": {"uv": [48, 407], "uv_size": [-12, 13]},
								"down": {"uv": [60, 420], "uv_size": [-12, -13]}
							}
						},
						{
							"origin": [-7.15, 110, -30.8],
							"size": [14.3, 4.4, 13.2],
							"uv": {
								"north": {"uv": [36, 420], "uv_size": [-13, 4]},
								"east": {"uv": [48, 420], "uv_size": [-12, 4]},
								"south": {"uv": [61, 420], "uv_size": [-13, 4]},
								"west": {"uv": [73, 420], "uv_size": [-12, 4]},
								"up": {"uv": [48, 407], "uv_size": [-12, 13]},
								"down": {"uv": [60, 420], "uv_size": [-12, -13]}
							}
						},
						{
							"origin": [-7.15, 110, -7.7],
							"size": [14.3, 4.4, 15.4],
							"uv": {
								"north": {"uv": [36, 420], "uv_size": [-13, 4]},
								"east": {"uv": [50, 420], "uv_size": [-14, 4]},
								"south": {"uv": [63, 420], "uv_size": [-13, 4]},
								"west": {"uv": [77, 420], "uv_size": [-14, 4]},
								"up": {"uv": [50, 407], "uv_size": [-14, 13]},
								"down": {"uv": [64, 420], "uv_size": [-14, -13]}
							}
						}
					]
				}
			]
		}
	]
}